{
  "generatedAt": "2026-04-21T09:58:50.593Z",
  "url": "https://api.skolverket.se/planned-educations/v4/school-units/17669293/statistics/gr",
  "acceptHeader": "application/vnd.skolverket.plannededucations.api.v4.hal+json",
  "json": {
    "status": "OK",
    "message": "Success",
    "body": {
      "schoolUnit": "17669293",
      "specialTeacherPositions": [
        {
          "value": ".",
          "valueType": "MISSING",
          "timePeriod": "2025/26"
        },
        {
          "value": ".",
          "valueType": "MISSING",
          "timePeriod": "2024/25"
        },
        {
          "value": ".",
          "valueType": "MISSING",
          "timePeriod": "2023/24"
        },
        {
          "value": ".",
          "valueType": "MISSING",
          "timePeriod": "2022/23"
        }
      ],
      "studentsPerTeacherQuota": [
        {
          "value": "..",
          "valueType": "OMITTED_DUE_TO_BASED_ON_FEW_PUPILS",
          "timePeriod": "2025/26"
        },
        {
          "value": "..",
          "valueType": "OMITTED_DUE_TO_BASED_ON_FEW_PUPILS",
          "timePeriod": "2024/25"
        },
        {
          "value": "2,7",
          "valueType": "EXISTS",
          "timePeriod": "2023/24"
        },
        {
          "value": "4,3",
          "valueType": "EXISTS",
          "timePeriod": "2022/23"
        }
      ],
      "certifiedTeachersQuota": [
        {
          "value": "..",
          "valueType": "OMITTED_DUE_TO_BASED_ON_FEW_PUPILS",
          "timePeriod": "2025/26"
        },
        {
          "value": "..",
          "valueType": "OMITTED_DUE_TO_BASED_ON_FEW_PUPILS",
          "timePeriod": "2024/25"
        },
        {
          "value": "94,0",
          "valueType": "EXISTS",
          "timePeriod": "2023/24"
        },
        {
          "value": "71,1",
          "valueType": "EXISTS",
          "timePeriod": "2022/23"
        }
      ],
      "docLinks": null,
      "specialEducatorsQuota": [
        {
          "value": "..",
          "valueType": "OMITTED_DUE_TO_BASED_ON_FEW_PUPILS",
          "timePeriod": "2025/26"
        },
        {
          "value": "..",
          "valueType": "OMITTED_DUE_TO_BASED_ON_FEW_PUPILS",
          "timePeriod": "2024/25"
        },
        {
          "value": "34,4",
          "valueType": "EXISTS",
          "timePeriod": "2023/24"
        },
        {
          "value": "15,2",
          "valueType": "EXISTS",
          "timePeriod": "2022/23"
        }
      ],
      "totalNumberOfPupils": [
        {
          "value": "cirka 10",
          "valueType": "EXISTS",
          "timePeriod": "2025/26"
        }
      ],
      "ratioOfPupilsIn6thGradeWithAllSubjectsPassed": [
        {
          "value": null,
          "valueType": "MISSING",
          "timePeriod": null
        }
      ],
      "averageResultNationalTestsSubjectSVE6thGrade": [
        {
          "value": "..",
          "valueType": "OMITTED_DUE_TO_BASED_ON_FEW_PUPILS",
          "timePeriod": "2023/24"
        }
      ],
      "averageResultNationalTestsSubjectENG6thGrade": [
        {
          "value": "..",
          "valueType": "OMITTED_DUE_TO_BASED_ON_FEW_PUPILS",
          "timePeriod": "2023/24"
        }
      ],
      "averageResultNationalTestsSubjectMA6thGrade": [
        {
          "value": ".",
          "valueType": "MISSING",
          "timePeriod": "2023/24"
        }
      ],
      "averageResultNationalTestsSubjectSVA6thGrade": [
        {
          "value": ".",
          "valueType": "MISSING",
          "timePeriod": "2023/24"
        }
      ],
      "averageResultNationalTestsSubjectSVE9thGrade": [
        {
          "value": ".",
          "valueType": "MISSING",
          "timePeriod": "2024/25"
        },
        {
          "value": ".",
          "valueType": "MISSING",
          "timePeriod": "2023/24"
        },
        {
          "value": ".",
          "valueType": "MISSING",
          "timePeriod": "2022/23"
        },
        {
          "value": ".",
          "valueType": "MISSING",
          "timePeriod": "2021/22"
        }
      ],
      "averageResultNationalTestsSubjectENG9thGrade": [
        {
          "value": ".",
          "valueType": "MISSING",
          "timePeriod": "2024/25"
        },
        {
          "value": ".",
          "valueType": "MISSING",
          "timePeriod": "2023/24"
        },
        {
          "value": ".",
          "valueType": "MISSING",
          "timePeriod": "2022/23"
        },
        {
          "value": ".",
          "valueType": "MISSING",
          "timePeriod": "2021/22"
        }
      ],
      "averageResultNationalTestsSubjectMA9thGrade": [
        {
          "value": ".",
          "valueType": "MISSING",
          "timePeriod": "2024/25"
        },
        {
          "value": ".",
          "valueType": "MISSING",
          "timePeriod": "2023/24"
        },
        {
          "value": ".",
          "valueType": "MISSING",
          "timePeriod": "2022/23"
        },
        {
          "value": ".",
          "valueType": "MISSING",
          "timePeriod": "2021/22"
        }
      ],
      "averageResultNationalTestsSubjectSVA9thGrade": [
        {
          "value": ".",
          "valueType": "MISSING",
          "timePeriod": "2024/25"
        },
        {
          "value": ".",
          "valueType": "MISSING",
          "timePeriod": "2023/24"
        },
        {
          "value": ".",
          "valueType": "MISSING",
          "timePeriod": "2022/23"
        },
        {
          "value": ".",
          "valueType": "MISSING",
          "timePeriod": "2021/22"
        }
      ],
      "ratioOfPupilsIn9thGradeWithAllSubjectsPassed": [
        {
          "value": ".",
          "valueType": "MISSING",
          "timePeriod": "2024/25"
        },
        {
          "value": ".",
          "valueType": "MISSING",
          "timePeriod": "2023/24"
        },
        {
          "value": ".",
          "valueType": "MISSING",
          "timePeriod": "2022/23"
        },
        {
          "value": ".",
          "valueType": "MISSING",
          "timePeriod": "2021/22"
        }
      ],
      "averageGradesMeritRating9thGrade": [
        {
          "value": "..",
          "valueType": "OMITTED_DUE_TO_BASED_ON_FEW_PUPILS",
          "timePeriod": "2024/25"
        },
        {
          "value": "..",
          "valueType": "OMITTED_DUE_TO_BASED_ON_FEW_PUPILS",
          "timePeriod": "2023/24"
        },
        {
          "value": "..",
          "valueType": "OMITTED_DUE_TO_BASED_ON_FEW_PUPILS",
          "timePeriod": "2022/23"
        },
        {
          "value": ".",
          "valueType": "MISSING",
          "timePeriod": "2021/22"
        }
      ],
      "ratioOfPupils9thGradeEligibleForNationalProgramYR": [
        {
          "value": ".",
          "valueType": "MISSING",
          "timePeriod": "2024/25"
        },
        {
          "value": ".",
          "valueType": "MISSING",
          "timePeriod": "2023/24"
        },
        {
          "value": ".",
          "valueType": "MISSING",
          "timePeriod": "2022/23"
        },
        {
          "value": ".",
          "valueType": "MISSING",
          "timePeriod": "2021/22"
        }
      ],
      "ratioOfPupils9thGradeEligibleForNationalProgramES": [
        {
          "value": ".",
          "valueType": "MISSING",
          "timePeriod": "2024/25"
        },
        {
          "value": ".",
          "valueType": "MISSING",
          "timePeriod": "2023/24"
        },
        {
          "value": ".",
          "valueType": "MISSING",
          "timePeriod": "2022/23"
        },
        {
          "value": ".",
          "valueType": "MISSING",
          "timePeriod": "2021/22"
        }
      ],
      "ratioOfPupils9thGradeEligibleForNationalProgramSAEKHU": [
        {
          "value": ".",
          "valueType": "MISSING",
          "timePeriod": "2024/25"
        },
        {
          "value": ".",
          "valueType": "MISSING",
          "timePeriod": "2023/24"
        },
        {
          "value": ".",
          "valueType": "MISSING",
          "timePeriod": "2022/23"
        },
        {
          "value": ".",
          "valueType": "MISSING",
          "timePeriod": "2021/22"
        }
      ],
      "ratioOfPupils9thGradeEligibleForNationalProgramNATE": [
        {
          "value": ".",
          "valueType": "MISSING",
          "timePeriod": "2024/25"
        },
        {
          "value": ".",
          "valueType": "MISSING",
          "timePeriod": "2023/24"
        },
        {
          "value": ".",
          "valueType": "MISSING",
          "timePeriod": "2022/23"
        },
        {
          "value": ".",
          "valueType": "MISSING",
          "timePeriod": "2021/22"
        }
      ],
      "_links": {
        "self": {
          "href": "https://api.skolverket.se/planned-educations/v3/school-units/17669293/statistics/gr"
        }
      }
    }
  }
}