{
  "generatedAt": "2026-04-21T09:53:31.112Z",
  "url": "https://api.skolverket.se/planned-educations/v4/school-units/15641642/statistics/gr",
  "acceptHeader": "application/vnd.skolverket.plannededucations.api.v4.hal+json",
  "json": {
    "status": "OK",
    "message": "Success",
    "body": {
      "schoolUnit": "15641642",
      "specialTeacherPositions": [
        {
          "value": "..",
          "valueType": "OMITTED_DUE_TO_BASED_ON_FEW_PUPILS",
          "timePeriod": "2025/26"
        },
        {
          "value": "..",
          "valueType": "OMITTED_DUE_TO_BASED_ON_FEW_PUPILS",
          "timePeriod": "2024/25"
        },
        {
          "value": "1,0",
          "valueType": "EXISTS",
          "timePeriod": "2023/24"
        },
        {
          "value": "0,8",
          "valueType": "EXISTS",
          "timePeriod": "2022/23"
        },
        {
          "value": "1,0",
          "valueType": "EXISTS",
          "timePeriod": "2021/22"
        }
      ],
      "studentsPerTeacherQuota": [
        {
          "value": "12,5",
          "valueType": "EXISTS",
          "timePeriod": "2025/26"
        },
        {
          "value": "12,5",
          "valueType": "EXISTS",
          "timePeriod": "2024/25"
        },
        {
          "value": "13,9",
          "valueType": "EXISTS",
          "timePeriod": "2023/24"
        },
        {
          "value": "13,3",
          "valueType": "EXISTS",
          "timePeriod": "2022/23"
        },
        {
          "value": "12,9",
          "valueType": "EXISTS",
          "timePeriod": "2021/22"
        }
      ],
      "certifiedTeachersQuota": [
        {
          "value": "71,6",
          "valueType": "EXISTS",
          "timePeriod": "2025/26"
        },
        {
          "value": "63,5",
          "valueType": "EXISTS",
          "timePeriod": "2024/25"
        },
        {
          "value": "72,8",
          "valueType": "EXISTS",
          "timePeriod": "2023/24"
        },
        {
          "value": "81,3",
          "valueType": "EXISTS",
          "timePeriod": "2022/23"
        },
        {
          "value": "73,2",
          "valueType": "EXISTS",
          "timePeriod": "2021/22"
        }
      ],
      "docLinks": null,
      "specialEducatorsQuota": [
        {
          "value": "3,8",
          "valueType": "EXISTS",
          "timePeriod": "2025/26"
        },
        {
          "value": "3,9",
          "valueType": "EXISTS",
          "timePeriod": "2024/25"
        },
        {
          "value": "3,9",
          "valueType": "EXISTS",
          "timePeriod": "2023/24"
        },
        {
          "value": "3,7",
          "valueType": "EXISTS",
          "timePeriod": "2022/23"
        },
        {
          "value": "3,6",
          "valueType": "EXISTS",
          "timePeriod": "2021/22"
        }
      ],
      "totalNumberOfPupils": [
        {
          "value": "cirka 260",
          "valueType": "EXISTS",
          "timePeriod": "2025/26"
        }
      ],
      "ratioOfPupilsIn6thGradeWithAllSubjectsPassed": [
        {
          "value": "75,4",
          "valueType": "EXISTS",
          "timePeriod": "2024/25"
        }
      ],
      "averageResultNationalTestsSubjectSVE6thGrade": [
        {
          "value": "12,9",
          "valueType": "EXISTS",
          "timePeriod": "2024/25"
        },
        {
          "value": "13,0",
          "valueType": "EXISTS",
          "timePeriod": "2023/24"
        },
        {
          "value": "14,5",
          "valueType": "EXISTS",
          "timePeriod": "2022/23"
        },
        {
          "value": "13,9",
          "valueType": "EXISTS",
          "timePeriod": "2021/22"
        }
      ],
      "averageResultNationalTestsSubjectENG6thGrade": [
        {
          "value": "15,9",
          "valueType": "EXISTS",
          "timePeriod": "2024/25"
        },
        {
          "value": "15,9",
          "valueType": "EXISTS",
          "timePeriod": "2023/24"
        },
        {
          "value": "14,3",
          "valueType": "EXISTS",
          "timePeriod": "2022/23"
        },
        {
          "value": "14,4",
          "valueType": "EXISTS",
          "timePeriod": "2021/22"
        }
      ],
      "averageResultNationalTestsSubjectMA6thGrade": [
        {
          "value": "11,7",
          "valueType": "EXISTS",
          "timePeriod": "2024/25"
        },
        {
          "value": "12,1",
          "valueType": "EXISTS",
          "timePeriod": "2023/24"
        },
        {
          "value": "11,0",
          "valueType": "EXISTS",
          "timePeriod": "2022/23"
        },
        {
          "value": "13,0",
          "valueType": "EXISTS",
          "timePeriod": "2021/22"
        }
      ],
      "averageResultNationalTestsSubjectSVA6thGrade": [
        {
          "value": "..",
          "valueType": "OMITTED_DUE_TO_BASED_ON_FEW_PUPILS",
          "timePeriod": "2024/25"
        },
        {
          "value": "..",
          "valueType": "OMITTED_DUE_TO_BASED_ON_FEW_PUPILS",
          "timePeriod": "2023/24"
        },
        {
          "value": "..",
          "valueType": "OMITTED_DUE_TO_BASED_ON_FEW_PUPILS",
          "timePeriod": "2022/23"
        },
        {
          "value": "..",
          "valueType": "OMITTED_DUE_TO_BASED_ON_FEW_PUPILS",
          "timePeriod": "2021/22"
        }
      ],
      "averageResultNationalTestsSubjectSVE9thGrade": [],
      "averageResultNationalTestsSubjectENG9thGrade": [],
      "averageResultNationalTestsSubjectMA9thGrade": [],
      "averageResultNationalTestsSubjectSVA9thGrade": [],
      "ratioOfPupilsIn9thGradeWithAllSubjectsPassed": [],
      "averageGradesMeritRating9thGrade": [],
      "ratioOfPupils9thGradeEligibleForNationalProgramYR": [],
      "ratioOfPupils9thGradeEligibleForNationalProgramES": [],
      "ratioOfPupils9thGradeEligibleForNationalProgramSAEKHU": [],
      "ratioOfPupils9thGradeEligibleForNationalProgramNATE": [],
      "_links": {
        "self": {
          "href": "https://api.skolverket.se/planned-educations/v3/school-units/15641642/statistics/gr"
        }
      }
    }
  }
}