{
  "generatedAt": "2026-04-21T09:49:12.498Z",
  "url": "https://api.skolverket.se/planned-educations/v4/school-units/42164778/statistics/gr",
  "acceptHeader": "application/vnd.skolverket.plannededucations.api.v4.hal+json",
  "json": {
    "status": "OK",
    "message": "Success",
    "body": {
      "schoolUnit": "42164778",
      "specialTeacherPositions": [
        {
          "value": ".",
          "valueType": "MISSING",
          "timePeriod": "2025/26"
        },
        {
          "value": ".",
          "valueType": "MISSING",
          "timePeriod": "2024/25"
        },
        {
          "value": ".",
          "valueType": "MISSING",
          "timePeriod": "2023/24"
        },
        {
          "value": ".",
          "valueType": "MISSING",
          "timePeriod": "2022/23"
        },
        {
          "value": ".",
          "valueType": "MISSING",
          "timePeriod": "2021/22"
        }
      ],
      "studentsPerTeacherQuota": [
        {
          "value": "13,9",
          "valueType": "EXISTS",
          "timePeriod": "2025/26"
        },
        {
          "value": "17,0",
          "valueType": "EXISTS",
          "timePeriod": "2024/25"
        },
        {
          "value": "12,7",
          "valueType": "EXISTS",
          "timePeriod": "2023/24"
        },
        {
          "value": "12,8",
          "valueType": "EXISTS",
          "timePeriod": "2022/23"
        },
        {
          "value": "14,7",
          "valueType": "EXISTS",
          "timePeriod": "2021/22"
        }
      ],
      "certifiedTeachersQuota": [
        {
          "value": "73,0",
          "valueType": "EXISTS",
          "timePeriod": "2025/26"
        },
        {
          "value": "79,7",
          "valueType": "EXISTS",
          "timePeriod": "2024/25"
        },
        {
          "value": "67,4",
          "valueType": "EXISTS",
          "timePeriod": "2023/24"
        },
        {
          "value": "71,0",
          "valueType": "EXISTS",
          "timePeriod": "2022/23"
        },
        {
          "value": "72,1",
          "valueType": "EXISTS",
          "timePeriod": "2021/22"
        }
      ],
      "docLinks": null,
      "specialEducatorsQuota": [
        {
          "value": "8,0",
          "valueType": "EXISTS",
          "timePeriod": "2025/26"
        },
        {
          "value": "5,4",
          "valueType": "EXISTS",
          "timePeriod": "2024/25"
        },
        {
          "value": "6,3",
          "valueType": "EXISTS",
          "timePeriod": "2023/24"
        },
        {
          "value": "5,3",
          "valueType": "EXISTS",
          "timePeriod": "2022/23"
        },
        {
          "value": "4,8",
          "valueType": "EXISTS",
          "timePeriod": "2021/22"
        }
      ],
      "totalNumberOfPupils": [
        {
          "value": "cirka 860",
          "valueType": "EXISTS",
          "timePeriod": "2025/26"
        }
      ],
      "ratioOfPupilsIn6thGradeWithAllSubjectsPassed": [
        {
          "value": "71,4",
          "valueType": "EXISTS",
          "timePeriod": "2024/25"
        }
      ],
      "averageResultNationalTestsSubjectSVE6thGrade": [
        {
          "value": "12,5",
          "valueType": "EXISTS",
          "timePeriod": "2024/25"
        },
        {
          "value": "14,2",
          "valueType": "EXISTS",
          "timePeriod": "2023/24"
        },
        {
          "value": "13,8",
          "valueType": "EXISTS",
          "timePeriod": "2022/23"
        },
        {
          "value": "14,1",
          "valueType": "EXISTS",
          "timePeriod": "2021/22"
        }
      ],
      "averageResultNationalTestsSubjectENG6thGrade": [
        {
          "value": "15,9",
          "valueType": "EXISTS",
          "timePeriod": "2024/25"
        },
        {
          "value": "16,7",
          "valueType": "EXISTS",
          "timePeriod": "2023/24"
        },
        {
          "value": "15,6",
          "valueType": "EXISTS",
          "timePeriod": "2022/23"
        },
        {
          "value": "15,0",
          "valueType": "EXISTS",
          "timePeriod": "2021/22"
        }
      ],
      "averageResultNationalTestsSubjectMA6thGrade": [
        {
          "value": "11,7",
          "valueType": "EXISTS",
          "timePeriod": "2024/25"
        },
        {
          "value": "12,7",
          "valueType": "EXISTS",
          "timePeriod": "2023/24"
        },
        {
          "value": "10,3",
          "valueType": "EXISTS",
          "timePeriod": "2022/23"
        },
        {
          "value": "12,7",
          "valueType": "EXISTS",
          "timePeriod": "2021/22"
        }
      ],
      "averageResultNationalTestsSubjectSVA6thGrade": [
        {
          "value": "9,5",
          "valueType": "EXISTS",
          "timePeriod": "2024/25"
        },
        {
          "value": "10,5",
          "valueType": "EXISTS",
          "timePeriod": "2023/24"
        },
        {
          "value": "11,1",
          "valueType": "EXISTS",
          "timePeriod": "2022/23"
        },
        {
          "value": "6,8",
          "valueType": "EXISTS",
          "timePeriod": "2021/22"
        }
      ],
      "averageResultNationalTestsSubjectSVE9thGrade": [
        {
          "value": "13,1",
          "valueType": "EXISTS",
          "timePeriod": "2024/25"
        },
        {
          "value": "14,9",
          "valueType": "EXISTS",
          "timePeriod": "2023/24"
        },
        {
          "value": "15,5",
          "valueType": "EXISTS",
          "timePeriod": "2022/23"
        },
        {
          "value": "15,3",
          "valueType": "EXISTS",
          "timePeriod": "2021/22"
        }
      ],
      "averageResultNationalTestsSubjectENG9thGrade": [
        {
          "value": "15,9",
          "valueType": "EXISTS",
          "timePeriod": "2024/25"
        },
        {
          "value": "16,3",
          "valueType": "EXISTS",
          "timePeriod": "2023/24"
        },
        {
          "value": "16,5",
          "valueType": "EXISTS",
          "timePeriod": "2022/23"
        },
        {
          "value": "16,5",
          "valueType": "EXISTS",
          "timePeriod": "2021/22"
        }
      ],
      "averageResultNationalTestsSubjectMA9thGrade": [
        {
          "value": "11,5",
          "valueType": "EXISTS",
          "timePeriod": "2024/25"
        },
        {
          "value": "14,2",
          "valueType": "EXISTS",
          "timePeriod": "2023/24"
        },
        {
          "value": "15,0",
          "valueType": "EXISTS",
          "timePeriod": "2022/23"
        },
        {
          "value": "14,4",
          "valueType": "EXISTS",
          "timePeriod": "2021/22"
        }
      ],
      "averageResultNationalTestsSubjectSVA9thGrade": [
        {
          "value": "9,8",
          "valueType": "EXISTS",
          "timePeriod": "2024/25"
        },
        {
          "value": "8,8",
          "valueType": "EXISTS",
          "timePeriod": "2023/24"
        },
        {
          "value": "8,2",
          "valueType": "EXISTS",
          "timePeriod": "2022/23"
        },
        {
          "value": "8,3",
          "valueType": "EXISTS",
          "timePeriod": "2021/22"
        }
      ],
      "ratioOfPupilsIn9thGradeWithAllSubjectsPassed": [
        {
          "value": "77,6",
          "valueType": "EXISTS",
          "timePeriod": "2024/25"
        },
        {
          "value": "83,1",
          "valueType": "EXISTS",
          "timePeriod": "2023/24"
        },
        {
          "value": "84,2",
          "valueType": "EXISTS",
          "timePeriod": "2022/23"
        },
        {
          "value": "88,5",
          "valueType": "EXISTS",
          "timePeriod": "2021/22"
        },
        {
          "value": "73,6",
          "valueType": "EXISTS",
          "timePeriod": "2020/21"
        }
      ],
      "averageGradesMeritRating9thGrade": [
        {
          "value": "237,0",
          "valueType": "EXISTS",
          "timePeriod": "2024/25"
        },
        {
          "value": "250,1",
          "valueType": "EXISTS",
          "timePeriod": "2023/24"
        },
        {
          "value": "264,0",
          "valueType": "EXISTS",
          "timePeriod": "2022/23"
        },
        {
          "value": "256,2",
          "valueType": "EXISTS",
          "timePeriod": "2021/22"
        },
        {
          "value": "228,1",
          "valueType": "EXISTS",
          "timePeriod": "2020/21"
        }
      ],
      "ratioOfPupils9thGradeEligibleForNationalProgramYR": [
        {
          "value": "86,5",
          "valueType": "EXISTS",
          "timePeriod": "2024/25"
        },
        {
          "value": "90,4",
          "valueType": "EXISTS",
          "timePeriod": "2023/24"
        },
        {
          "value": "90,2",
          "valueType": "EXISTS",
          "timePeriod": "2022/23"
        },
        {
          "value": "91,3",
          "valueType": "EXISTS",
          "timePeriod": "2021/22"
        },
        {
          "value": "86,2",
          "valueType": "EXISTS",
          "timePeriod": "2020/21"
        }
      ],
      "ratioOfPupils9thGradeEligibleForNationalProgramES": [
        {
          "value": "85,9",
          "valueType": "EXISTS",
          "timePeriod": "2024/25"
        },
        {
          "value": "89,7",
          "valueType": "EXISTS",
          "timePeriod": "2023/24"
        },
        {
          "value": "89,5",
          "valueType": "EXISTS",
          "timePeriod": "2022/23"
        },
        {
          "value": "91,3",
          "valueType": "EXISTS",
          "timePeriod": "2021/22"
        },
        {
          "value": "86,2",
          "valueType": "EXISTS",
          "timePeriod": "2020/21"
        }
      ],
      "ratioOfPupils9thGradeEligibleForNationalProgramSAEKHU": [
        {
          "value": "84,7",
          "valueType": "EXISTS",
          "timePeriod": "2024/25"
        },
        {
          "value": "87,5",
          "valueType": "EXISTS",
          "timePeriod": "2023/24"
        },
        {
          "value": "89,5",
          "valueType": "EXISTS",
          "timePeriod": "2022/23"
        },
        {
          "value": "91,3",
          "valueType": "EXISTS",
          "timePeriod": "2021/22"
        },
        {
          "value": "83,9",
          "valueType": "EXISTS",
          "timePeriod": "2020/21"
        }
      ],
      "ratioOfPupils9thGradeEligibleForNationalProgramNATE": [
        {
          "value": "81,8",
          "valueType": "EXISTS",
          "timePeriod": "2024/25"
        },
        {
          "value": "88,2",
          "valueType": "EXISTS",
          "timePeriod": "2023/24"
        },
        {
          "value": "88,0",
          "valueType": "EXISTS",
          "timePeriod": "2022/23"
        },
        {
          "value": "91,3",
          "valueType": "EXISTS",
          "timePeriod": "2021/22"
        },
        {
          "value": "86,2",
          "valueType": "EXISTS",
          "timePeriod": "2020/21"
        }
      ],
      "_links": {
        "self": {
          "href": "https://api.skolverket.se/planned-educations/v3/school-units/42164778/statistics/gr"
        }
      }
    }
  }
}